pyr34/__init__.py
pyr34/client.py
pyr34/models.py
pyr34/tags.py
pyr34-0.2.1.dist-info/licenses/LICENSE
pyr34-0.2.1.dist-info/METADATA
pyr34-0.2.1.dist-info/WHEEL
pyr34-0.2.1.dist-info/top_level.txt
pyr34-0.2.1.dist-info/RECORD
