Metadata-Version: 2.4
Name: pyr34
Version: 0.2.1
Summary: Wrapper around the JSON/XML rule34.xxx API.
Author: Connor Tippets
License-Expression: GPL-3.0-only
Project-URL: Repository, https://github.com/ConnorTippets/pyr34
Requires-Python: >=3.10
License-File: LICENSE
Dynamic: license-file
